simplepg/__init__.py
simplepg/db.py
simplepg-0.1.5.dist-info/LICENSE
simplepg-0.1.5.dist-info/WHEEL
simplepg-0.1.5.dist-info/METADATA
simplepg-0.1.5.dist-info/RECORD
