Metadata-Version: 2.1
Name: simplepg
Version: 0.1.5
Summary: Simple PostgreSQL connections
License: Apache-2.0
Author: Mysterious Ben
Author-email: datascience@tuta.io
Requires-Python: >=3.8.1,<4.0
Classifier: License :: OSI Approved :: Apache Software License
Classifier: Programming Language :: Python :: 3
Classifier: Programming Language :: Python :: 3.9
Classifier: Programming Language :: Python :: 3.10
Classifier: Programming Language :: Python :: 3.11
Requires-Dist: loguru (>=0.5.0,<0.6.0)
Requires-Dist: psycopg2 (>=2.9.5,<3.0.0)
